pytest_factoryboy_state/__init__.py
pytest_factoryboy_state/_version.py
pytest_factoryboy_state/plugin.py
pytest_factoryboy_state-1.0.0.dist-info/LICENSE
pytest_factoryboy_state-1.0.0.dist-info/METADATA
pytest_factoryboy_state-1.0.0.dist-info/WHEEL
pytest_factoryboy_state-1.0.0.dist-info/entry_points.txt
pytest_factoryboy_state-1.0.0.dist-info/top_level.txt
pytest_factoryboy_state-1.0.0.dist-info/RECORD
