Metadata-Version: 2.1
Name: pytest-factoryboy-state
Version: 1.0.0
Summary: Simple factoryboy random state management
Home-page: https://github.com/hrother/pytest-factoryboy-state
Author: Holger Rother
Author-email: hrother@hrother.org
Maintainer: Holger Rother
Maintainer-email: hrother@hrother.org
License: MIT
Keywords: pytest factoryboy
Platform: UNKNOWN
Classifier: Development Status :: 5 - Production/Stable
Classifier: Framework :: Pytest
Classifier: Intended Audience :: Developers
Classifier: Topic :: Software Development :: Testing
Classifier: Programming Language :: Python
Classifier: Programming Language :: Python :: 3
Classifier: Programming Language :: Python :: 3.7
Classifier: Programming Language :: Python :: 3.8
Classifier: Programming Language :: Python :: 3.9
Classifier: Programming Language :: Python :: 3.10
Classifier: Programming Language :: Python :: 3 :: Only
Classifier: Programming Language :: Python :: Implementation :: CPython
Classifier: Operating System :: OS Independent
Classifier: License :: OSI Approved :: MIT License
Requires-Python: >=3.7
Requires-Dist: pytest (>=5.0)
Requires-Dist: factory-boy (>=3.1.0)
Provides-Extra: dev
Requires-Dist: pre-commit ; extra == 'dev'
Requires-Dist: tox ; extra == 'dev'
